pydateinfer/__init__.py
pydateinfer/date_elements.py
pydateinfer/examples.yaml
pydateinfer/infer.py
pydateinfer/meta.yaml
pydateinfer/ruleproc.py
pydateinfer/tests.py
py_dateinfer-0.4.5.dist-info/LICENSE
py_dateinfer-0.4.5.dist-info/METADATA
py_dateinfer-0.4.5.dist-info/WHEEL
py_dateinfer-0.4.5.dist-info/top_level.txt
py_dateinfer-0.4.5.dist-info/RECORD
