Metadata-Version: 2.1
Name: py-dateinfer
Version: 0.4.5
Summary: Infers date format from examples, by using a series of pattern matching and rewriting rules to compute a "best guess" datetime.strptime format string give a list of example date strings.
Home-page: https://github.com/jeffreystarr/dateinfer
Author: Jeffrey Starr
Author-email: will@pedalwrencher.com
License: Apache Software License 2.0
Keywords: pydateinfer
Platform: UNKNOWN
Classifier: Development Status :: 4 - Beta
Classifier: Intended Audience :: Developers
Classifier: License :: OSI Approved :: Apache Software License
Classifier: Operating System :: OS Independent
Classifier: Programming Language :: Python
Classifier: Programming Language :: Python :: 3
Classifier: Topic :: Software Development :: Libraries :: Python Modules
Requires-Python: !=3.0.*, !=3.1.*, !=3.2.*, !=3.3.*, !=3.4.*
Requires-Dist: wheel
Requires-Dist: pytz
